bulletin_board_client-0.3.3.dist-info/METADATA
bulletin_board_client-0.3.3.dist-info/WHEEL
bulletin_board_client/helper.py
bulletin_board_client/__init__.py
bulletin_board_client/bulletin_board_client.cpython-311-x86_64-linux-gnu.so
bulletin_board_client-0.3.3.dist-info/RECORD
