Metadata-Version: 2.4
Name: bulletin_board_client
Version: 0.3.3
Classifier: Topic :: Database
Classifier: Topic :: Software Development :: Debuggers
Classifier: License :: OSI Approved :: Apache Software License
Classifier: Programming Language :: Rust
Classifier: Programming Language :: Python :: Implementation :: CPython
Classifier: Programming Language :: Python :: Implementation :: PyPy
Requires-Dist: numpy
Summary: Python client for BulletinBoard
Keywords: object_storage,database,debugging,python,client
License: Apache-2.0
Requires-Python: >=3.5
Project-URL: Repository, https://github.com/YShoji-HEP/BulletinBoard
Project-URL: funding, https://buymeacoffee.com/yshojihep
Project-URL: sponsor, https://github.com/sponsors/YShoji-HEP
